_nulapack.cpython-311-x86_64-linux-gnu.so
nulapack/__init__.py
nulapack/cholesky.py
nulapack/gauss_seidel.py
nulapack/jacobi.py
nulapack/thomas.py
nulapack-1.0.0.dist-info/METADATA
nulapack-1.0.0.dist-info/WHEEL
nulapack-1.0.0.dist-info/RECORD
